Workbook

Sheet Packages
A1: NGO Monthly Packages — Aurelius / Kreatif Atelier
A2: Prices exclude GST. Third-party costs (ad spend, WhatsApp message fees, printing, travel, flight permissions, hosting, software licences) are funded by the NGO.
B4: PLATINUM | C4: GOLD | D4: SILVER
A5: Monthly price (₹) | B5: 40000 | C5: 25000 | D5: 15000
A6: Best for | B6: Established NGO, 15–60 staff, funders to report to | C6: Growing NGO, 5–20 staff, building credibility | D6: Small NGO, under 5 staff, needs to be visible
A7: Primary objective served | B7: Donations, volunteers and CSR partnerships | C7: Awareness and credibility | D7: Presence and consistency
A8: Aurelius codes included | B8: DM-01, DM-04, DM-06, DM-07, DM-10, DM-15, DM-24, FM-04, FM-24, SEO-02, SEO-04, AN-03 | C8: DM-01, DM-07, DM-24, FM-04, FM-24, SEO-02 (light), SEO-04, AN-03 | D8: DM-01, FM-04, FM-24 (limited)
A9: Platforms managed | B9: 4 — Instagram, Facebook, LinkedIn, YouTube Shorts | C9: 3 — Instagram, Facebook, LinkedIn | D9: 2 — Instagram, Facebook
A10: Social posts per month | B10: 16 | C10: 8 | D10: 4
A11: Reels / short videos per month | B11: 6, up to 60s | C11: 4, up to 45s | D11: 2, up to 30s
A12: Content calendar | B12: Yes, dated, by the 25th | C12: Yes, dated, by the 25th | D12: Yes, simple list, by the 25th
A13: Captions, hashtags, scheduling | B13: Included, platform-adapted | C13: Included, platform-adapted | D13: Included, cross-posted
A14: Impact story (DM-24) | B14: 1 per month, 700–900 words | C14: 1 per month, 500–700 words | D14: Not included
A15: Email newsletter (DM-07) | B15: 1 per month | C15: 1 per month | D15: Not included
A16: WhatsApp broadcast (DM-10) | B16: 1 per month | C16: Add-on | D16: Not included
A17: Appeal asset set | B17: 1 per month | C17: 1 per quarter | D17: Not included
A18: Full campaign kit | B18: 1 per quarter | C18: Add-on | D18: Not included
A19: On-page SEO (SEO-02) | B19: 4 pages per month | C19: 2 pages per month | D19: Not included
A20: Google Business Profile (SEO-04) | B20: Managed — 2 posts, reviews, Q&A | C20: Light — 1 post, reviews | D20: Not included
A21: Donor lifecycle (DM-15) | B21: Maintained | C21: Not included | D21: Not included
A22: Live dashboard (AN-03) | B22: Yes, continuous | C22: Yes, shared access | D22: Not included
... A27: NGO asset deadline | B27: 18th of the prior month | C27: 18th of the prior month | D27: 18th of the prior month
A28: Estimated delivery hours per month | B28: 38.25 | C28: 22.8 | D28: 9.45
A30: Posts beyond the tier count are an add-on — see the Add-ons sheet. Figures supplied by the agency, October 2026; hours are estimates, not verified costs.

Sheet Platinum
A1: PLATINUM — ₹40,000 / month
A2: Estimated 38.25 delivery hours per month. Roles: AL = account lead, CD = content designer / editor, NGO-A = the NGO's single named approver.
A4: Deliverable | B4: Qty / month | C4: Format and scope | D4: NGO supplies | E4: Produce → approve → publish | F4: Output measure | G4: Excluded from the deliverable
A5: Content calendar (DM-01) | B5: 1 | C5: Dated grid of every post, reel, email and campaign for the coming month, one approval | D5: Programme dates, events, festivals, funder milestones | E5: AL → NGO-A | F5: Delivered by the 25th | G5: Mid-month rewrites after approval
A6: Social posts (DM-01) | B6: 16 | C6: Static and carousel from the locked BR-17 template kit, sized per platform | D6: Photos, programme facts, consent status | E6: CD → NGO-A → CD | F6: Published count vs planned | G6: Bespoke illustration, new template formats, per-post redesign, posts beyond 16
A7: Reels / short videos (FM-04, FM-24) | B7: 6 | C7: Up to 60 seconds, edited from NGO footage; captions, licensed music, light motion | D7: Raw footage or photo sets | E7: CD → NGO-A → CD | F7: Published count; views, completion | G7: Filming, voice-over artists, animation beyond light motion
A8: Short-form video strategy (DM-06) | B8: Ongoing | C8: Hooks, formats and posting cadence chosen deliberately rather than per post | D8: Programme context | E8: AL | F8: Format performance review | G8: Production beyond the 6 reels
A9: Platforms managed | B9: 4 | C9: Instagram, Facebook, LinkedIn, YouTube Shorts — adapted per platform, not blind cross-posting | D9: Admin access via Business Suite roles | E9: CD | F9: Posting consistency per platform | G9: Any fifth platform
A10: Impact story (DM-24) | B10: 1 | C10: 700–900 words for the website, atomised into 2 posts and the newsletter | D10: Programme data, quotes, documented consent | E10: CD → NGO-A → CMS | F10: Published; sessions, time on page | G10: Fieldwork, interviews conducted by the agency
A11: Supporter newsletter (DM-07) | B11: 1 | C11: Templated HTML email, built once and refilled monthly | D11: Contact list, consent basis, sending platform | E11: CD → NGO-A → AL sends | F11: Delivered; opens and clicks | G11: List building, platform fees, re-permissioning
A12: WhatsApp broadcast (DM-10) | B12: 1 | C12: One approved broadcast to opted-in supporters or volunteers | D12: Opted-in list, Business account | E12: AL → NGO-A → AL | F12: Delivered; read and reply rate | G12: Conversation handling, replies, message fees
A13: LinkedIn / CSR visibility (DM-04) | B13: 4 of the 16 posts | C13: Posts angled at CSR and institutional audiences | D13: Partnership news, compliance credentials | E13: CD → NGO-A → CD | F13: Decision-maker reach; page views | G13: Outbound messaging to CSR contacts
A14: Appeal asset set | B14: 1 | C14: 3 creatives plus copy for one donation, volunteer or event ask | D14: The ask, the target, the landing URL | E14: CD → NGO-A → CD | F14: Click-through to the tracked page | G14: Donation page build, payment setup, ad spend
A15: Full campaign kit | B15: 1 per quarter | C15: Landing-page copy, 6 creatives, 2 emails, UTM plan, post-campaign readout | D15: Campaign goal, dates, page access | E15: AL + CD → NGO-A → AL | F15: Tracked conversions on the campaign journey | G15: Page build, ad management, media spend
... A21: Meetings | B21: 2 + quarterly | C21: 45-min monthly review, 30-min mid-month check-in, 90-min quarterly strategy | D21: Attendance by a decision-maker | E21: AL | F21: Held on schedule | G21: Ad-hoc calls, NGO internal or board meetings
A23: Anything beyond these quantities is quoted from the Add-ons sheet. Scope agreed with the agency, October 2026.

Sheet Gold
A1: GOLD — ₹25,000 / month
A2: Estimated 22.8 delivery hours per month. Roles: AL = account lead, CD = content designer / editor, NGO-A = the NGO's single named approver.
A4: Deliverable | B4: Qty / month | C4: Format and scope | D4: NGO supplies | E4: Produce → approve → publish | F4: Output measure | G4: Excluded from the deliverable
A5: Content calendar (DM-01) | B5: 1 | C5: Dated grid of posts, reels and the monthly email, one approval | D5: Programme dates, events, festivals | E5: AL → NGO-A | F5: Delivered by the 25th | G5: Mid-month rewrites after approval
A6: Social posts (DM-01) | B6: 8 | C6: Static and carousel from the template kit, adapted per platform | D6: Photos, programme facts, consent status | E6: CD → NGO-A → CD | F6: Published count vs planned | G6: Bespoke illustration, new formats, posts beyond 8
A7: Reels / short videos (FM-04, FM-24) | B7: 4 | C7: Up to 45 seconds, edited from NGO-supplied footage, captioned | D7: Raw footage or photo sets | E7: CD → NGO-A → CD | F7: Published count; views | G7: Filming, voice-over, animation
A8: Platforms managed | B8: 3 | C8: Instagram, Facebook, LinkedIn | D8: Admin access via Business Suite roles | E8: CD | F8: Posting consistency | G8: Any fourth platform
A9: Impact story (DM-24) | B9: 1 | C9: 500–700 words for the website, atomised into 1 post and the newsletter | D9: Programme data, quotes, consent | E9: CD → NGO-A → CMS | F9: Published; sessions | G9: Fieldwork, interviews by the agency
A10: Supporter newsletter (DM-07) | B10: 1 | C10: Templated email, refilled monthly, single send | D10: Contact list, consent basis, platform | E10: CD → NGO-A → AL sends | F10: Delivered; opens and clicks | G10: List building, platform fees
A11: Appeal asset set | B11: 1 per quarter | C11: 3 creatives plus copy for one donation, volunteer or event ask | D11: The ask and the landing URL | E11: CD → NGO-A → CD | F11: Click-through to the tracked page | G11: Donation page build, ad spend
A12: On-page SEO (SEO-02) | B12: 2 pages | C12: Titles, meta descriptions, headings, call-to-action copy | D12: CMS access or publishing contact | E12: AL → NGO-A → AL | F12: Impressions and clicks | G12: Technical SEO, speed, migrations
A13: Google Business Profile (SEO-04) | B13: Ongoing, light | C13: 1 profile post, photo refresh, review responses | D13: Hours, address, photos | E13: AL | F13: Profile views and actions | G13: Review removal, dispute resolution
A14: Dashboard access (AN-03) | B14: Continuous | C14: Shared Looker Studio dashboard on client-owned sources | D14: Analytics access | E14: AL | F14: Uptime; data freshness | G14: Custom modelling, offline data entry
A15: Monthly report | B15: 1 | C15: 2–3 pages: deliverables vs plan, core KPIs vs last month, 3 actions | D15: Offline donation and volunteer numbers | E15: AL → QC → NGO-A | F15: Delivered by the 7th | G15: Board presentations, custom analysis
A16: Meetings | B16: 1 | C16: 45-minute monthly review call | D16: Attendance by a decision-maker | E16: AL | F16: Held on schedule | G16: Ad-hoc calls, mid-month check-in
A18: Anything beyond these quantities is quoted from the Add-ons sheet. Scope agreed with the agency, October 2026.

Sheet Silver
A1: SILVER — ₹15,000 / month
A2: Estimated 9.45 delivery hours per month. Roles: AL = account lead, CD = content designer / editor, NGO-A = the NGO's single named approver.
A4: Deliverable | B4: Qty / month | C4: Format and scope | D4: NGO supplies | E4: Produce → approve → publish | F4: Output measure | G4: Excluded from the deliverable
A5: Content calendar (DM-01) | B5: 1 | C5: Simple dated list of the month's posts, one approval | D5: Programme dates and events | E5: AL → NGO-A | F5: Delivered by the 25th | G5: Mid-month rewrites after approval
A6: Social posts (DM-01) | B6: 4 | C6: Static and carousel from the template kit; one creative set cross-posted to both platforms | D6: Photos and programme facts, consent status | E6: CD → NGO-A → CD | F6: Published count vs planned | G6: Platform-specific variants, posts beyond 4
A7: Reels / short videos (FM-04, FM-24) | B7: 2 | C7: Up to 30 seconds, simple edit of NGO-supplied footage, captioned | D7: Raw footage or photo sets | E7: CD → NGO-A → CD | F7: Published count; views | G7: Filming, motion graphics, music beyond the library
A8: Platforms managed | B8: 2 | C8: Instagram and Facebook | D8: Admin access via Business Suite roles | E8: CD | F8: Posting consistency | G8: Any third platform
A9: Captions and hashtags | B9: All posts | C9: Written from the agreed caption framework; reusable hashtag sets | D9: Approved terminology and names | E9: CD → NGO-A | F9: Part of batch approval | G9: Per-caption rewriting after sign-off
A10: Scheduling and publishing | B10: All posts | C10: Queued in the scheduling tool, published on the calendar dates | D10: Timely batch approval | E10: CD | F10: On-time publishing rate | G10: Mid-month reschedules
A11: Monthly report | B11: 1 | C11: 1 page: what was published, reach, engagement rate, follower change, 2 observations | D11: — | E11: AL → NGO-A | F11: Delivered by the 7th | G11: KPI targets, SEO or website data, custom analysis
A12: Meetings | B12: 1 | C12: 30-minute monthly call | D12: Attendance | E12: AL | F12: Held on schedule | G12: Ad-hoc calls, mid-month contact
A14: Anything beyond these quantities is quoted from the Add-ons sheet. Scope agreed with the agency, October 2026.

Sheet Add-ons
A1: Add-on, setup and project menu — list prices
A2: List prices exclude GST. Discount by removing scope, never by cutting the rate. Unit prices are shown in blue because they are the inputs the Quote builder reads.
A4: Category | B4: Add-on / item | C4: Aurelius code | D4: Unit price (₹) | E4: Basis and notes
A5: Recurring | B5: Additional 4 social posts | C5: DM-01 | D5: 3000 | E5: Per month, on top of the tier count
A6: Recurring | B6: Additional 2 reels or short videos | C6: FM-04, FM-24 | D6: 4000 | E6: Per month
A7: Recurring | B7: Additional platform managed | C7: DM-01 | D7: 3000 | E7: Per month, per platform
A8: Recurring | B8: Short-form video growth strategy (added to Gold) | C8: DM-06 | D8: 4000 | E8: Per month
A9: Recurring | B9: WhatsApp broadcasts (added to Gold) | C9: DM-10 | D9: 3500 | E9: Per month, plus platform message fees funded by the NGO
A10: Recurring | B10: Extra email campaign beyond the monthly newsletter | C10: DM-07 | D10: 3500 | E10: Each
A11: Recurring | B11: Marketing automation upkeep | C11: DM-08 | D11: 4000 | E11: Per month, after the build
A12: Recurring | B12: AI content system upkeep | C12: TP-12 | D12: 5000 | E12: Per month, after the build
A13: Recurring | B13: Local volunteer and donor lead generation | C13: LG-14 | D13: 8000 | E13: Per month
A14: Recurring | B14: Google Ad Grant management | C14: AD-01 | D14: 12000 | E14: Per month. Verify grant eligibility and policy compliance before selling
A15: Recurring | B15: Meta Ads management | C15: AD-03 | D15: 10000 | E15: Per month, or 18% of spend if higher. Media spend funded by the NGO
A16: Recurring | B16: Fractional CMO and growth advisory, 8 hours | C16: AV-06 | D16: 25000 | E16: Per month
... A44: Project | B44: Press release written and distributed | C44: PR-02 | D44: 10000 | E44: Per release, plus distribution costs
A46: Edit a blue price here and the Quote builder updates. List prices set by the agency, October 2026.

Sheet Quote builder
A1: Quote builder
A2: EDIT ONLY THE YELLOW CELLS: the tier in B4, the months in B6, and a quantity in column E below. Every other cell is a formula.
A4: Tier (type Platinum, Gold or Silver) | B4: Gold | C4: Tier name must match a column heading on the Packages sheet exactly.
A5: Monthly retainer (₹) | B5: =IFERROR(INDEX(Packages!$B$5:$D$5,MATCH($B$4,Packages!$B$4:$D$4,0)),0) -> 25000
A6: Months contracted | B6: 12
A8: Category | B8: Add-on / item | C8: Code | D8: Unit price (₹) | E8: Qty | F8: Line total (₹)
A9: ='Add-ons'!A5 -> Recurring | B9: ='Add-ons'!B5 -> Additional 4 social posts | C9: ='Add-ons'!C5 -> DM-01 | D9: ='Add-ons'!D5 -> 3000 | E9: 1 | F9: =D9*E9 -> 3000
A10: ='Add-ons'!A6 -> Recurring | B10: ='Add-ons'!B6 -> Additional 2 reels or short videos | C10: ='Add-ons'!C6 -> FM-04, FM-24 | D10: ='Add-ons'!D6 -> 4000 | E10: 0 | F10: =D10*E10 -> 0
A11: ='Add-ons'!A7 -> Recurring | B11: ='Add-ons'!B7 -> Additional platform managed | C11: ='Add-ons'!C7 -> DM-01 | D11: ='Add-ons'!D7 -> 3000 | E11: 0 | F11: =D11*E11 -> 0
A12: ='Add-ons'!A8 -> Recurring | B12: ='Add-ons'!B8 -> Short-form video growth strategy (added to Gold) | C12: ='Add-ons'!C8 -> DM-06 | D12: ='Add-ons'!D8 -> 4000 | E12: 0 | F12: =D12*E12 -> 0
A13: ='Add-ons'!A9 -> Recurring | B13: ='Add-ons'!B9 -> WhatsApp broadcasts (added to Gold) | C13: ='Add-ons'!C9 -> DM-10 | D13: ='Add-ons'!D9 -> 3500 | E13: 0 | F13: =D13*E13 -> 0
A14: ='Add-ons'!A10 -> Recurring | B14: ='Add-ons'!B10 -> Extra email campaign beyond the monthly newsletter | C14: ='Add-ons'!C10 -> DM-07 | D14: ='Add-ons'!D10 -> 3500 | E14: 0 | F14: =D14*E14 -> 0
A15: ='Add-ons'!A11 -> Recurring | B15: ='Add-ons'!B11 -> Marketing automation upkeep | C15: ='Add-ons'!C11 -> DM-08 | D15: ='Add-ons'!D11 -> 4000 | E15: 0 | F15: =D15*E15 -> 0
A16: ='Add-ons'!A12 -> Recurring | B16: ='Add-ons'!B12 -> AI content system upkeep | C16: ='Add-ons'!C12 -> TP-12 | D16: ='Add-ons'!D12 -> 5000 | E16: 0 | F16: =D16*E16 -> 0
A17: ='Add-ons'!A13 -> Recurring | B17: ='Add-ons'!B13 -> Local volunteer and donor lead generation | C17: ='Add-ons'!C13 -> LG-14 | D17: ='Add-ons'!D13 -> 8000 | E17: 0 | F17: =D17*E17 -> 0
A18: ='Add-ons'!A14 -> Recurring | B18: ='Add-ons'!B14 -> Google Ad Grant management | C18: ='Add-ons'!C14 -> AD-01 | D18: ='Add-ons'!D14 -> 12000 | E18: 0 | F18: =D18*E18 -> 0
A19: ='Add-ons'!A15 -> Recurring | B19: ='Add-ons'!B15 -> Meta Ads management | C19: ='Add-ons'!C15 -> AD-03 | D19: ='Add-ons'!D15 -> 10000 | E19: 0 | F19: =D19*E19 -> 0
A20: ='Add-ons'!A16 -> Recurring | B20: ='Add-ons'!B16 -> Fractional CMO and growth advisory, 8 hours | C20: ='Add-ons'!C16 -> AV-06 | D20: ='Add-ons'!D16 -> 25000 | E20: 0 | F20: =D20*E20 -> 0
... A48: ='Add-ons'!A44 -> Project | B48: ='Add-ons'!B44 -> Press release written and distributed | C48: ='Add-ons'!C44 -> PR-02 | D48: ='Add-ons'!D44 -> 10000 | E48: 0 | F48: =D48*E48 -> 0
A50: Recurring add-ons (₹ / month) | F50: =SUMIFS($F$9:$F$48,$A$9:$A$48,"Recurring") -> 3000
A51: One-time setup (₹) | F51: =SUMIFS($F$9:$F$48,$A$9:$A$48,"Setup") -> 0
A52: Projects (₹) | F52: =SUMIFS($F$9:$F$48,$A$9:$A$48,"Project") -> 0
A53: Month 1 invoice — retainer + recurring + one-time (₹) | F53: =$B$5+F50+F51+F52 -> 28000
A54: Ongoing monthly invoice from month 2 (₹) | F54: =$B$5+F50 -> 28000
A55: Total contract value over the months in B6 (₹) | F55: =($B$5+F50)*$B$6+F51+F52 -> 336000
A57: All figures exclude GST. Media spend, WhatsApp message fees, printing, venue, travel, flight permissions, hosting and software licences are additional and funded by the NGO.

Sheet Economics
A1: Delivery economics — internal only
A2: INTERNAL. Never share with a client. Hours are agency estimates built from assumed task durations, not verified costs — replace them with time-tracking data after two months of live delivery.
A4: Assumptions — edit the yellow cells
A5: Blended internal cost per productive hour (₹) | B5: 350 | C5: Derived from a content designer at ~₹28,000/month and an account lead at ~₹60,000/month, each delivering ~120 productive hours in a 160-hour month. Agency estimate.
A6: Productive hours per person per month | B6: 120
A7: Buffer applied to estimated hours | B7: 0.1
A8: Fixed monthly overhead (₹) | B8: 120000
A11: Line | B11: Platinum | C11: Gold | D11: Silver | E11: Notes
A12: Monthly fee (₹) | B12: 40000 | C12: 25000 | D12: 15000 | E12: Fixed price
A13: Strategy, calendar and account management (h) | B13: 3.5 | C13: 2.5 | D13: 1.25 | E13: Agency estimate
A14: Design and content production (h) | B14: 20.5 | C14: 12.3 | D14: 4.2 | E14: Agency estimate
A15: Publishing, SEO and optimisation (h) | B15: 7.5 | C15: 3.25 | D15: 0.75 | E15: Agency estimate
A16: Reporting and meetings (h) | B16: 4.25 | C16: 2.75 | D16: 2 | E16: Agency estimate
A17: QC, admin and client communication (h) | B17: 2.5 | C17: 2 | D17: 1.25 | E17: Agency estimate
A18: Software and assets allocated (₹) | B18: 600 | C18: 500 | D18: 350 | E18: Per client per month
A19: Estimated total hours | B19: =SUM(B13:B17) -> 38.25 | C19: =SUM(C13:C17) -> 22.8 | D19: =SUM(D13:D17) -> 9.45
A20: Budgeted hours with buffer | B20: =B19*(1+$B$7) -> 42.075 | C20: =C19*(1+$B$7) -> 25.08 | D20: =D19*(1+$B$7) -> 10.395
A21: Delivery cost — labour (₹) | B21: =B20*$B$5 -> 14726.25 | C21: =C20*$B$5 -> 8778 | D21: =D20*$B$5 -> 3638.25
A22: Gross contribution (₹) | B22: =B12-B21-B18 -> 24673.75 | C22: =C12-C21-C18 -> 15722 | D22: =D12-D21-D18 -> 11011.75
A23: Gross margin | B23: =IFERROR(B22/B12,0) -> 0.61684375 | C23: =IFERROR(C22/C12,0) -> 0.62888 | D23: =IFERROR(D22/D12,0) -> 0.73411667
A24: Revenue per delivery hour (₹) | B24: =IFERROR(B12/B20,0) -> 950.6833 | C24: =IFERROR(C12/C20,0) -> 996.81021 | D24: =IFERROR(D12/D20,0) -> 1443.0014
A25: Hours at which the tier earns nothing | B25: =IFERROR((B12-B18)/$B$5,0) -> 112.57143 | C25: =IFERROR((C12-C18)/$B$5,0) -> 70 | D25: =IFERROR((D12-D18)/$B$5,0) -> 41.857143
A27: Portfolio check — enter the number of clients on each tier
A28: Clients on this tier | B28: 2 | C28: 4 | D28: 4
A29: Gross contribution from the portfolio (₹) | B29: =SUMPRODUCT($B$22:$D$22,$B$28:$D$28) -> 156282.5
A30: Budgeted delivery hours required | B30: =SUMPRODUCT($B$20:$D$20,$B$28:$D$28) -> 226.05
A31: Delivery people required | B31: =IFERROR(B30/$B$6,0) -> 1.88375
A32: Contribution after fixed overhead (₹) | B32: =B29-$B$8 -> 36282.5
A34: Gross contribution is not net profit: founder and sales time, accounting, non-allocated software, bad debt and tax sit below this line. One account lead can hold about 10 NGO relationships before report quality drops, which binds before production hours do.
